<questions>
    <question type="o_que">
        <type_id>O que é</type_id> <entity>PicPay</entity>?
    </question>
    <question type="o_que">
        <type_id>O que é</type_id> a <entity>KOIN</entity>?
    </question>
    <question type="o_que">
        <type_id>O que</type_id> significa cada <aspect>status</aspect> de meu <entity>pedido</entity>?
    </question>
    <question type="o_que">
        <type_id>O que é</type_id> a <entity>NuConta</entity>?
    </question>
    <question type="o_que">
        <type_id>O que é</type_id> o <entity>Nubank</entity>?
    </question>
    <question type="o_que">
        <type_id>O que é</type_id> a <entity>Conta PJ</entity>?
    </question>
    <question type="o_que">
        <type_id>O que é</type_id> a <entity>Nota Fiscal Eletrônica – NF-e</entity>?
    </question>
    <question type="o_que">
        <type_id>O Que é</type_id> uma <entity>DANFE</entity> e onde localizo o <aspect>numero</aspect> da <entity>Chave de Acesso</entity>?
    </question>
    <question type="o_que">
        <type_id>O que é</type_id> o <entity>PAR-Q</entity>?
    </question>
    <question type="o_que">
        <type_id>O que é</type_id> o <entity>freepass</entity>?
    </question>
    <question type="o_que">
        <type_id>O que é</type_id> <entity>manutenção anual</entity>?
    </question>
    <question type="o_que">
        <type_id>O que é</type_id> <entity>taxa de adesão</entity>?
    </question>
    <question type="o_que">
        Eu tenho <entity>cobranças</entity> em <aspect>aberto</aspect> ? <type_id>O que</type_id> devo <intention>fazer</intention>?
    </question>
    <question type="o_que">
        <aspect>Não consigo</aspect> <intention>acessar</intention> <entity>minha conta</entity>. <type_id>O que</type_id> <intention>fazer</intention>?
    </question>
    <question type="o_que">
        <type_id>O que</type_id> significa "<entity>Cadastro de Vendedores</entity>"?
    </question>
    <question type="o_que">
        Tenho uma <entity>conta Vendedor</entity>, mas não gostaria que meu <aspect>nome</aspect> aparecesse para meus <entity>clientes</entity>. <type_id>O que</type_id> <intention>fazer</intention>?
    </question>
    <question type="o_que">
        <type_id>O que é</type_id> um <entity>e-mail adicional</entity>?
    </question>
    <question type="o_que">
        Não consigo <intention>acessar</intention> <entity>minha conta</entity>. <type_id>O que</type_id> <intention>fazer</intention>?
    </question>
    <question type="o_que">
        <type_id>O que é</type_id> <entity>Cartão da Conta</entity>?
    </question>
    <question type="o_que">
        <type_id>O que é</type_id> e como <intention>fazer</intention> uma <entity>Transferência para Contato</entity>?
    </question>
    <question type="o_que">
        Fiz uma <entity>recarga de celular</entity> para o <aspect>número errado</aspect>. <type_id>O que</type_id> devo <intention>fazer</intention>?
    </question>
    <question type="o_que">
        O <entity>empréstimo</entity> ainda não está <aspect>disponível</aspect>. <type_id>O que</type_id> posso <intention>fazer</intention>?
    </question>
    <question type="o_que">
        A minha <intention>solicitação</intention> de <aspect>portabilidade</aspect> de <entity>salário</entity> foi <aspect>reprovada</aspect>. <type_id>O que</type_id> aconteceu?
    </question>
    <question type="o_que">
        <type_id>O que</type_id> faço quando o <entity>salário</entity> está com o <aspect>valor incorreto</aspect>?
    </question>
    <question type="o_que">
        <type_id>O que é</type_id> o <entity>Aponte e Pag (QR Code)</entity>?
    </question>
    <question type="o_que">
        <type_id>O que é</type_id> a <entity>Transferência TED</entity>?
    </question>
    <question type="o_que">
        <type_id>O que é</type_id> o <entity>aplicativo PagBank</entity>?
    </question>
    <question type="o_que">
        <type_id>O que é</type_id> <entity>Verificação de Conta</entity>?
    </question>
<!--    <question type="o_que">
        <type_id>O que é</type_id> saldo bloqueado na minha Conta do Pagseguro?
    </question> -->
    <question type="o_que">
        <type_id>O que é</type_id> o <entity>"Código de Segurança" via SMS</entity> e para que serve?
    </question>
    <question type="o_que">
        <type_id>O que é</type_id> <entity>Celular Seguro</entity>?
    </question>
    <question type="o_que">
        <type_id>O que é</type_id> <entity>SMS Token</entity>?
    </question>
    <question type="o_que">
        <type_id>O que é</type_id> <entity>Disputa</entity>?
    </question>
    <question type="o_que">
        <type_id>O que é</type_id> <entity>Moderação</entity>?
    </question>
    <question type="o_que">
        Não consigo <intention>entrar</intention> em um <aspect>acordo</aspect> com o <entity>vendedor</entity>. <type_id>O que</type_id> faço?
    </question>
    <question type="o_que">
        <type_id>O que é</type_id> <entity>grupo de testes</entity>?
    </question>
    <question type="o_que">
        <type_id>O que é</type_id> <entity>TestFlight</entity>?
    </question>
    <question type="o_que">
        <type_id>O que é</type_id> <entity>Verificação de Conta</entity>?
    </question>
    <question type="o_que">
        <type_id>O que é</type_id> <aspect>saldo bloqueado</aspect> na minha <entity>Conta do Pagseguro</entity>?
    </question>
    <question type="o_que">
        <type_id>O que é</type_id> o <entity>"Código de Segurança" via SMS</entity> e para que serve?
    </question>
    <question type="o_que">
        <type_id>O que é</type_id> <entity>Celular Seguro</entity>?
    </question>
    <question type="o_que">
        <type_id>O que é</type_id> <entity>SMS Token</entity>?
    </question>
    <question type="o_que">
        <aspect>Não estou</aspect> recebendo o <entity>SMS Token</entity> para <intention>realizar</intention> uma <aspect>transação</aspect>. <type_id>O que</type_id> devo <intention>fazer</intention>?
    </question>
    <question type="o_que">
        <type_id>O que é</type_id> <entity>Token de Voz</entity>?
    </question>
    <question type="o_que">
        <type_id>O que</type_id> são <entity>notificações do sistema</entity>?
    </question>
    <question type="o_que">
        <type_id>O que é</type_id> <entity>phishing</entity>?
    </question>
    <question type="o_que">
        <type_id>O que é</type_id> <entity>Nota Fiscal Eletrônica (NF-e)</entity> e para quê serve?
    </question>
    <question type="o_que">
        <type_id>O que é</type_id> <entity>Contestação</entity>?
    </question>
    <question type="o_que">
        <type_id>O que</type_id> <intention>fazer</intention> quando há <entity>contestação</entity> de uma <entity>venda</entity> feita pelo <entity>Leitor de Crédito</entity>?
    </question>
    <question type="o_que">
        <type_id>O que é</type_id> <entity>Moderação</entity>?
    </question>
    <question type="o_que">
        <aspect>Não consigo</aspect> <intention>entrar</intention> em um acordo com o <entity>vendedor</entity>. <type_id>O que</type_id> faço?
    </question>
    <question type="o_que">
        <type_id>O que é</type_id> <entity>Disputa</entity>?
    </question>
    <question type="o_que">
        <type_id>O que é</type_id> um <entity>Caso Jurídico</entity>?
    </question>
    <question type="o_que">
        <type_id>O que</type_id> significa o <entity>Aviso de Recebimento (A.R.)</entity>?
    </question>
    <question type="o_que">
        Meu <entity>produto/serviço</entity> não foi <aspect>entregue</aspect>. <type_id>O que</type_id> posso <intention>fazer</intention>?
    </question>
    <question type="o_que">
        <type_id>O que é</type_id> <entity>marketplace<entity>?
    </question>
    <question type="o_que">
        <type_id>O que é<type_id> o <entity>Retira Fácil</entity>?
    </question>
    <question type="o_que">
        <type_id>O que é</type_id> o <entity>Frete Hoje</entity>?
    </question>
    <question type="o_que">
        <type_id>O que</type_id> significa <entity>pedido em análise</entity>?
    </question>
    <question type="o_que">
        <type_id>O que</type_id> é a <entity>nota fiscal eletrônica</entity>?
    </question>
    <question type="o_que">
        <type_id>O que</type_id> é o <entity>DANFE</entity>?
    </question>
    <question type="o_que">
        <type_id>O que</type_id> é <entity>Nota Fiscal Paulista</entity>?
    </question>
    <question type="o_que">
        <type_id>O que</type_id> é <entity>Nota Fiscal Eletrônica</entity>?
    </question>
    <question type="o_que">
        <type_id>O que</type_id> é <entity>Danfe</entity>?
    </question>
    <question type="o_que">
        <type_id>O que</type_id> é <entity>cupom de desconto</entity> e como <intention>utilizar</intention>?
    </question>
    <question type="o_que">
        Fiz o <entity>pagamento<entity> com <entity>dois cartões</entity> e um foi <aspect>reprovado<aspect>. <type_id>O que</type_id> acontece?
    </question>
    <question type="o_que">
        <type_id>O que</type_id> é <entity>Garantia Estendida</entity>?
    </question>
    <question type="o_que">
        <type_id>O que</type_id> é <entity>proteção contra roubo e furto</entity>?
    </question>
    <question type="o_que">
        <type_id>O que</type_id> é <entity>Marketplace</entity> / <entity>Vendedor parceiro</entity>?
    </question>
    <question type="o_que">
        <type_id>O que</type_id> é a <entity>Lista de Casamento</entity> e como ela funciona?
    </question>
    <question type="o_que">
        <type_id>O que</type_id> é <entity>compra expressa</entity>?
    </question>
    <question type="o_que">
        <type_id>O que</type_id> é <entity>capa ilustrativa</entity>?
    </question>
    <question type="o_que">
        <type_id>O que</type_id> <intention>verificar</intention> no ato da <aspect>entrega</aspect> do <entity>pedido</entity>?
    </question>
    <question type="o_que">
        <type_id>O que</type_id> é a <entity>Marisa.com.br</entity>?
    </question>
    <question type="o_que">
        Meu <entity>pedido</entity> está no <aspect>status de Recebido Pré-venda</aspect>, <type_id>o que</type_id> significa?
    </question>
    <question type="o_que">
        <type_id>O que</type_id> significa a <aspect>tag Pré-venda</aspect> nos <entity>produtos</entity>?
    </question>
    <question type="o_que">
        <type_id>O que</type_id> significa o <entity>botão TROCA</entity>, ao <aspect>lado dos dados do meu pedido</aspect> no site?
    </question>
    <question type="o_que">
        <type_id>O que</type_id> significa a informação no <entity>rastreamento</entity> de <aspect>Áreas com restrição de entrega domiciliar</aspect>
    </question>
    <question type="o_que">
        <type_id>O que</type_id> significa o status <entity>Em Análise do Posto Fiscal</entity>, no envio por Transportadora?
    </question>
    <question type="o_que">
        <type_id>O que</type_id> significam os status no <entity>rastreamento via transportadora -Total Express</entity>?
    </question>
</questions>